llp_learn/__about__.py
llp_learn/__init__.py
llp_learn/base.py
llp_learn/alter/__init__.py
llp_learn/alter/_base.py
llp_learn/alter/_classes.py
llp_learn/dllp/__init__.py
llp_learn/dllp/_classes.py
llp_learn/dllp/_loaders.py
llp_learn/em/__init__.py
llp_learn/em/_classes.py
llp_learn/llpfc/__init__.py
llp_learn/llpfc/_classes.py
llp_learn/llpfc/_loaders.py
llp_learn/llpfc/_make_groups.py
llp_learn/llpvat/__init__.py
llp_learn/llpvat/_classes.py
llp_learn/llpvat/_loaders.py
llp_learn/llpvat/_vat_loss.py
llp_learn/mixbag/__init__.py
llp_learn/mixbag/_classes.py
llp_learn/mixbag/_loaders.py
llp_learn/mixbag/_losses.py
llp_learn/model_selection/__init__.py
llp_learn/model_selection/_search.py
llp_learn/model_selection/_split.py
llp_learn/util/__init__.py
llp_learn/util/_util.py
llp_learn-1.6.0.dist-info/METADATA
llp_learn-1.6.0.dist-info/WHEEL
llp_learn-1.6.0.dist-info/licenses/LICENSE.txt
llp_learn-1.6.0.dist-info/RECORD
