Metadata-Version: 2.4
Name: llp-learn
Version: 1.6.0
Summary: Learning from Label Proportions (LLP) methods in Python
Project-URL: Documentation, https://github.com/gaabrielfranco/llp-learn#readme
Project-URL: Issues, https://github.com/gaabrielfranco/llp-learn/issues
Project-URL: Source, https://github.com/gaabrielfranco/llp-learn
Author-email: Gabriel Franco <gvfranco@bu.edu>
License-Expression: MIT
License-File: LICENSE.txt
Classifier: Development Status :: 4 - Beta
Classifier: Programming Language :: Python
Classifier: Programming Language :: Python :: 3.8
Classifier: Programming Language :: Python :: 3.9
Classifier: Programming Language :: Python :: 3.10
Classifier: Programming Language :: Python :: 3.11
Classifier: Programming Language :: Python :: Implementation :: CPython
Classifier: Programming Language :: Python :: Implementation :: PyPy
Requires-Python: >=3.8
Requires-Dist: joblib~=1.2.0
Requires-Dist: matplotlib~=3.7.1
Requires-Dist: numpy~=1.24.2
Requires-Dist: pandas~=1.5.3
Requires-Dist: scikit-learn~=1.2.2
Requires-Dist: scipy~=1.10.1
Requires-Dist: seaborn~=0.12.2
Requires-Dist: torch~=2.0.1
Requires-Dist: tqdm~=4.65.0
